containerutil/__init__.py
containerutil/__version__.py
containerutil/path.py
containerutil-0.2.0.dist-info/DESCRIPTION.rst
containerutil-0.2.0.dist-info/METADATA
containerutil-0.2.0.dist-info/RECORD
containerutil-0.2.0.dist-info/WHEEL
containerutil-0.2.0.dist-info/metadata.json
containerutil-0.2.0.dist-info/top_level.txt
