Metadata-Version: 2.0
Name: containerutil
Version: 0.2.0
Summary: Tools for inspecting contents of docker container filesystem.
Home-page: https://github.com/pavdmyt/containerutil
Author: Pavlo Dmytrenko
Author-email: mail@pavdmyt.com
License: MIT
Download-URL: https://github.com/pavdmyt/containerutil/archive/master.zip
Keywords: docker container path pathlib file type filesystem
Platform: any
Classifier: Intended Audience :: Developers
Classifier: Intended Audience :: System Administrators
Classifier: Operating System :: OS Independent
Classifier: Development Status :: 3 - Alpha
Classifier: Natural Language :: English
Classifier: License :: OSI Approved :: MIT License
Classifier: Programming Language :: Python
Classifier: Programming Language :: Python :: 2
Classifier: Programming Language :: Python :: 2.7
Classifier: Programming Language :: Python :: 3
Classifier: Programming Language :: Python :: 3.3
Classifier: Programming Language :: Python :: 3.4
Classifier: Programming Language :: Python :: 3.5
Classifier: Programming Language :: Python :: 3.6
Classifier: Programming Language :: Python :: Implementation :: CPython
Classifier: Programming Language :: Python :: Implementation :: PyPy
Classifier: Topic :: Software Development
Classifier: Topic :: Software Development :: Libraries :: Python Modules
Classifier: Topic :: System
Classifier: Topic :: System :: Filesystems
Classifier: Topic :: Utilities
